concave_uhull/__init__.py
concave_uhull/alpha_shape.py
concave_uhull/geometry.py
concave_uhull/graph.py
concave_uhull-0.2.7.dist-info/METADATA
concave_uhull-0.2.7.dist-info/WHEEL
concave_uhull-0.2.7.dist-info/RECORD
